hello_todo/__init__.py
hello_todo/cli.py
hello_todo/db.py
hello_todo/init_db.sql
hello_todo-0.1.5.dist-info/entry_points.txt
hello_todo-0.1.5.dist-info/WHEEL
hello_todo-0.1.5.dist-info/METADATA
hello_todo-0.1.5.dist-info/RECORD
