Metadata-Version: 2.1
Name: hello-todo
Version: 0.1.5
Summary: 
Home-page: UNKNOWN
License: UNKOWN
Author: Mathias Ngo
Author-email: ngo.mathias@gmail.com
Classifier: Programming Language :: Python :: 2
Classifier: Programming Language :: Python :: 2.7
Classifier: Programming Language :: Python :: 3
Classifier: Programming Language :: Python :: 3.4
Classifier: Programming Language :: Python :: 3.5
Classifier: Programming Language :: Python :: 3.6
Classifier: Programming Language :: Python :: 3.7
Requires-Dist: click (>=7.0,<8.0)
